weboasis/RENAME_SUMMARY.md
weboasis/REPOSITORY_STRUCTURE.md
weboasis/__init__.py
weboasis/requirements.txt
weboasis/setup.py
weboasis/utils.py
weboasis/video_cover.png
weboasis/act_book/README.md
weboasis/act_book/__init__.py
weboasis/act_book/controller.py
weboasis/act_book/operations.py
weboasis/act_book/book/__init__.py
weboasis/act_book/book/browser/__init__.py
weboasis/act_book/book/browser/extraction.py
weboasis/act_book/book/browser/interaction.py
weboasis/act_book/book/browser/navigation.py
weboasis/act_book/book/composite/__init__.py
weboasis/act_book/book/composite/forms.py
weboasis/act_book/book/composite/highlighting.py
weboasis/act_book/book/dom/__init__.py
weboasis/act_book/book/dom/selector.py
weboasis/act_book/book/general/__init__.py
weboasis/act_book/book/general/flow.py
weboasis/act_book/core/__init__.py
weboasis/act_book/core/automator_interface.py
weboasis/act_book/core/base.py
weboasis/act_book/core/registry.py
weboasis/act_book/engines/__init__.py
weboasis/act_book/engines/playwright/__init__.py
weboasis/act_book/engines/playwright/playwright_automator.py
weboasis/act_book/engines/selenium/__init__.py
weboasis/act_book/engines/selenium/selenium_automator.py
weboasis/agents/__init__.py
weboasis/agents/base.py
weboasis/agents/constants.py
weboasis/agents/dual_agent.py
weboasis/agents/types.py
weboasis/config/prompts.yaml
weboasis/javascript/add_outline_elements.js
weboasis/javascript/create_developper_panel.js
weboasis/javascript/extract_accessbility_tree.js
weboasis/javascript/frame_mark_elements.js
weboasis/javascript/hide_developer_elements.js
weboasis/javascript/identify_interactive_elements.js
weboasis/javascript/remove_outline_elements.js
weboasis/javascript/show_decision_making_process.js
weboasis/javascript/show_developer_elements.js
weboasis/ui_manager/__init__.py
weboasis/ui_manager/base_manager.py
weboasis/ui_manager/constants.py
weboasis/ui_manager/js_adapters.py
weboasis/ui_manager/playwright_manager.py
weboasis-0.1.4.dist-info/licenses/LICENSE
weboasis-0.1.4.dist-info/METADATA
weboasis-0.1.4.dist-info/WHEEL
weboasis-0.1.4.dist-info/top_level.txt
weboasis-0.1.4.dist-info/RECORD
