Metadata-Version: 2.4
Name: weboasis
Version: 0.1.4
Summary: A web agent framework for researchers to build and study web agents for real-world applications
Author-email: Siyang Liu <lsiyang@umich.edu>
License: Apache-2.0
Project-URL: Homepage, https://github.com/lsy641/WebOasis
Project-URL: Repository, https://github.com/lsy641/WebOasis
Project-URL: Documentation, https://github.com/lsy641/WebOasis
Project-URL: Issues, https://github.com/lsy641/WebOasis/issues
Classifier: Development Status :: 3 - Alpha
Classifier: Intended Audience :: Developers
Classifier: Intended Audience :: Science/Research
Classifier: License :: OSI Approved :: Apache Software License
Classifier: Programming Language :: Python :: 3
Classifier: Programming Language :: Python :: 3.10
Classifier: Programming Language :: Python :: 3.11
Classifier: Programming Language :: Python :: 3.12
Classifier: Programming Language :: Python :: 3.13
Classifier: Topic :: Software Development :: Libraries :: Python Modules
Classifier: Topic :: Scientific/Engineering :: Artificial Intelligence
Classifier: Topic :: Internet :: WWW/HTTP :: Browsers
Requires-Python: >=3.10
License-File: LICENSE
Requires-Dist: selenium>=4.0.0
Requires-Dist: playwright>=1.30.0
Requires-Dist: pyyaml>=6.0
Requires-Dist: requests>=2.28.0
Requires-Dist: beautifulsoup4>=4.11.0
Requires-Dist: lxml>=4.9.0
Provides-Extra: dev
Requires-Dist: pytest>=7.0.0; extra == "dev"
Requires-Dist: pytest-cov>=4.0.0; extra == "dev"
Requires-Dist: black>=22.0.0; extra == "dev"
Requires-Dist: flake8>=5.0.0; extra == "dev"
Requires-Dist: mypy>=1.0.0; extra == "dev"
Dynamic: license-file
